.bumpversion.cfg
LICENSE.txt
README.txt
pypackage.mk
requirements.txt
setup.json
setup.py
src/procgraph/__init__.py
src/procgraph/__pycache__/__init__.cpython-38.pyc
src/procgraph/block_utils/__init__.py
src/procgraph/block_utils/executables.py
src/procgraph/block_utils/file_io.py
src/procgraph/block_utils/image_checks.py
src/procgraph/block_utils/iterator_generator.py
src/procgraph/block_utils/natsort.py
src/procgraph/block_utils/textlog.py
src/procgraph/block_utils/__pycache__/__init__.cpython-38.pyc
src/procgraph/block_utils/__pycache__/executables.cpython-38.pyc
src/procgraph/block_utils/__pycache__/file_io.cpython-38.pyc
src/procgraph/block_utils/__pycache__/image_checks.cpython-38.pyc
src/procgraph/block_utils/__pycache__/iterator_generator.cpython-38.pyc
src/procgraph/block_utils/__pycache__/textlog.cpython-38.pyc
src/procgraph/components/__init__.py
src/procgraph/components/__pycache__/__init__.cpython-38.pyc
src/procgraph/components/debug_components/__init__.py
src/procgraph/components/debug_components/clock.py
src/procgraph/components/debug_components/constant.py
src/procgraph/components/debug_components/gain.py
src/procgraph/components/debug_components/identity.py
src/procgraph/components/debug_components/info.py
src/procgraph/components/debug_components/operations.py
src/procgraph/components/debug_components/printc.py
src/procgraph/components/debug_components/__pycache__/__init__.cpython-38.pyc
src/procgraph/components/debug_components/__pycache__/clock.cpython-38.pyc
src/procgraph/components/debug_components/__pycache__/constant.cpython-38.pyc
src/procgraph/components/debug_components/__pycache__/gain.cpython-38.pyc
src/procgraph/components/debug_components/__pycache__/identity.cpython-38.pyc
src/procgraph/components/debug_components/__pycache__/info.cpython-38.pyc
src/procgraph/components/debug_components/__pycache__/operations.cpython-38.pyc
src/procgraph/components/debug_components/__pycache__/printc.cpython-38.pyc
src/procgraph/core/__init__.py
src/procgraph_z6.egg-info/PKG-INFO
src/procgraph_z6.egg-info/SOURCES.txt
src/procgraph_z6.egg-info/dependency_links.txt
src/procgraph_z6.egg-info/entry_points.txt
src/procgraph_z6.egg-info/not-zip-safe
src/procgraph_z6.egg-info/requires.txt
src/procgraph_z6.egg-info/top_level.txt